{"shotchart": {"id": "350175", "quarters": {"1": {"awayTeam": {"players": [{"percentage": 40, "id": 9639293, "shots": []}, {"percentage": 0, "id": 9639295, "shots": [{"y": 80, "x": 157, "made": false, "time": {"s": 29, "m": 0}}, {"y": 155, "x": 85, "made": true, "time": {"s": 50, "m": 5}}]}, {"percentage": 50, "id": 9639297, "shots": [{"y": 50, "x": 138, "made": false, "time": {"s": 56, "m": 4}}]}, {"percentage": 0, "id": 9639299, "shots": [{"y": 105, "x": 246, "made": false, "time": {"s": 35, "m": 2}}, {"y": 59, "x": 261, "made": true, "time": {"s": 57, "m": 3}}]}, {"percentage": 37.5, "id": 9639301, "shots": [{"y": 50, "x": 203, "made": false, "time": {"s": 40, "m": 2}}, {"y": 35, "x": 164, "made": false, "time": {"s": 31, "m": 3}}, {"y": 32, "x": 81, "made": false, "time": {"s": 36, "m": 4}}, {"y": 37, "x": 122, "made": true, "time": {"s": 14, "m": 5}}]}, {"percentage": 40, "id": 9639303, "shots": [{"y": 151, "x": 198, "made": false, "time": {"s": 6, "m": 1}}, {"y": 132, "x": 103, "made": false, "time": {"s": 26, "m": 3}}, {"y": 151, "x": 92, "made": false, "time": {"s": 17, "m": 6}}]}, {"percentage": 0, "id": 9639305, "shots": [{"y": 54, "x": 136, "made": true, "time": {"s": 52, "m": 7}}, {"y": 39, "x": 151, "made": true, "time": {"s": 39, "m": 9}}]}, {"percentage": 0, "id": 9639311, "shots": []}, {"percentage": 0, "id": 9639313, "shots": []}, {"percentage": 0, "id": 9639317, "shots": []}, {"percentage": 0, "id": 9639319, "shots": [{"y": 78, "x": 196, "made": false, "time": {"s": 3, "m": 7}}, {"y": 48, "x": 166, "made": true, "time": {"s": 11, "m": 9}}]}, {"percentage": 0, "id": 9639323, "shots": [{"y": 46, "x": 159, "made": false, "time": {"s": 54, "m": 1}}, {"y": 64, "x": 128, "made": false, "time": {"s": 50, "m": 6}}, {"y": 40, "x": 119, "made": true, "time": {"s": 26, "m": 7}}]}], "percentage": 41.54}, "homeTeam": {"players": [{"percentage": 66.67, "id": 9639273, "shots": []}, {"percentage": 40, "id": 9639259, "shots": []}, {"percentage": 50, "id": 9639271, "shots": []}, {"percentage": 57.14, "id": 9639281, "shots": [{"y": 28, "x": 14, "made": true, "time": {"s": 12, "m": 8}}]}, {"percentage": 42.86, "id": 9639265, "shots": []}, {"percentage": 80, "id": 9639289, "shots": [{"y": 159, "x": 122, "made": false, "time": {"s": 40, "m": 3}}, {"y": 40, "x": 125, "made": true, "time": {"s": 43, "m": 4}}]}, {"percentage": 25, "id": 9639287, "shots": [{"y": 36, "x": 133, "made": true, "time": {"s": 50, "m": 0}}]}, {"percentage": 0, "id": 9639275, "shots": [{"y": 51, "x": 151, "made": true, "time": {"s": 22, "m": 9}}, {"y": 53, "x": 134, "made": false, "time": {"s": 59, "m": 9}}]}, {"percentage": 0, "id": 9639267, "shots": [{"y": 46, "x": 80, "made": false, "time": {"s": 16, "m": 7}}]}, {"percentage": 0, "id": 9639269, "shots": [{"y": 34, "x": 130, "made": true, "time": {"s": 56, "m": 2}}, {"y": 37, "x": 101, "made": false, "time": {"s": 10, "m": 6}}, {"y": 41, "x": 130, "made": true, "time": {"s": 34, "m": 6}}]}, {"percentage": 0, "id": 9639277, "shots": [{"y": 38, "x": 16, "made": true, "time": {"s": 24, "m": 1}}, {"y": 41, "x": 161, "made": true, "time": {"s": 18, "m": 2}}, {"y": 41, "x": 32, "made": true, "time": {"s": 23, "m": 4}}, {"y": 38, "x": 121, "made": false, "time": {"s": 5, "m": 5}}, {"y": 38, "x": 128, "made": true, "time": {"s": 31, "m": 5}}]}, {"percentage": 0, "id": 9639285, "shots": []}], "percentage": 48.15}, "number": 1}, "3": {"awayTeam": {"players": [{"percentage": 40, "id": 9639293, "shots": []}, {"percentage": 0, "id": 9639295, "shots": [{"y": 44, "x": 267, "made": false, "time": {"s": 20, "m": 28}}]}, {"percentage": 50, "id": 9639297, "shots": [{"y": 42, "x": 132, "made": false, "time": {"s": 46, "m": 20}}, {"y": 39, "x": 121, "made": false, "time": {"s": 43, "m": 22}}]}, {"percentage": 0, "id": 9639299, "shots": [{"y": 35, "x": 66, "made": true, "time": {"s": 11, "m": 21}}, {"y": 158, "x": 158, "made": false, "time": {"s": 11, "m": 22}}, {"y": 52, "x": 121, "made": false, "time": {"s": 51, "m": 27}}]}, {"percentage": 37.5, "id": 9639301, "shots": []}, {"percentage": 40, "id": 9639303, "shots": [{"y": 125, "x": 231, "made": true, "time": {"s": 47, "m": 21}}, {"y": 105, "x": 175, "made": true, "time": {"s": 33, "m": 24}}, {"y": 38, "x": 124, "made": false, "time": {"s": 46, "m": 28}}, {"y": 143, "x": 201, "made": false, "time": {"s": 59, "m": 29}}]}, {"percentage": 0, "id": 9639305, "shots": []}, {"percentage": 0, "id": 9639311, "shots": []}, {"percentage": 0, "id": 9639313, "shots": []}, {"percentage": 0, "id": 9639317, "shots": []}, {"percentage": 0, "id": 9639319, "shots": [{"y": 48, "x": 145, "made": false, "time": {"s": 2, "m": 26}}, {"y": 45, "x": 165, "made": false, "time": {"s": 35, "m": 26}}]}, {"percentage": 0, "id": 9639323, "shots": [{"y": 61, "x": 145, "made": false, "time": {"s": 20, "m": 23}}, {"y": 46, "x": 133, "made": true, "time": {"s": 34, "m": 25}}, {"y": 44, "x": 94, "made": true, "time": {"s": 52, "m": 26}}]}], "percentage": 41.54}, "homeTeam": {"players": [{"percentage": 66.67, "id": 9639273, "shots": [{"y": 38, "x": 125, "made": false, "time": {"s": 27, "m": 21}}]}, {"percentage": 40, "id": 9639259, "shots": []}, {"percentage": 50, "id": 9639271, "shots": []}, {"percentage": 57.14, "id": 9639281, "shots": [{"y": 125, "x": 227, "made": false, "time": {"s": 37, "m": 28}}]}, {"percentage": 42.86, "id": 9639265, "shots": []}, {"percentage": 80, "id": 9639289, "shots": [{"y": 68, "x": 244, "made": false, "time": {"s": 6, "m": 24}}, {"y": 45, "x": 142, "made": true, "time": {"s": 40, "m": 26}}]}, {"percentage": 25, "id": 9639287, "shots": [{"y": 52, "x": 132, "made": false, "time": {"s": 15, "m": 27}}, {"y": 34, "x": 228, "made": false, "time": {"s": 44, "m": 27}}]}, {"percentage": 0, "id": 9639275, "shots": [{"y": 114, "x": 129, "made": true, "time": {"s": 16, "m": 20}}]}, {"percentage": 0, "id": 9639267, "shots": [{"y": 52, "x": 58, "made": true, "time": {"s": 0, "m": 21}}, {"y": 156, "x": 134, "made": false, "time": {"s": 0, "m": 22}}, {"y": 48, "x": 142, "made": true, "time": {"s": 56, "m": 22}}, {"y": 39, "x": 221, "made": false, "time": {"s": 47, "m": 24}}, {"y": 52, "x": 142, "made": true, "time": {"s": 51, "m": 25}}]}, {"percentage": 0, "id": 9639269, "shots": [{"y": 41, "x": 152, "made": true, "time": {"s": 18, "m": 27}}, {"y": 42, "x": 165, "made": false, "time": {"s": 37, "m": 29}}]}, {"percentage": 0, "id": 9639277, "shots": []}, {"percentage": 0, "id": 9639285, "shots": []}], "percentage": 48.15}, "number": "3"}, "2": {"awayTeam": {"players": [{"percentage": 40, "id": 9639293, "shots": []}, {"percentage": 0, "id": 9639295, "shots": []}, {"percentage": 50, "id": 9639297, "shots": [{"y": 41, "x": 116, "made": false, "time": {"s": 45, "m": 11}}, {"y": 42, "x": 126, "made": true, "time": {"s": 50, "m": 12}}, {"y": 31, "x": 118, "made": true, "time": {"s": 40, "m": 14}}, {"y": 40, "x": 161, "made": false, "time": {"s": 38, "m": 15}}]}, {"percentage": 0, "id": 9639299, "shots": [{"y": 102, "x": 251, "made": true, "time": {"s": 22, "m": 17}}, {"y": 106, "x": 34, "made": true, "time": {"s": 5, "m": 18}}, {"y": 90, "x": 255, "made": false, "time": {"s": 25, "m": 18}}, {"y": 44, "x": 129, "made": true, "time": {"s": 51, "m": 18}}]}, {"percentage": 37.5, "id": 9639301, "shots": [{"y": 37, "x": 204, "made": true, "time": {"s": 56, "m": 16}}]}, {"percentage": 40, "id": 9639303, "shots": [{"y": 68, "x": 223, "made": true, "time": {"s": 8, "m": 15}}, {"y": 129, "x": 136, "made": false, "time": {"s": 43, "m": 18}}, {"y": 94, "x": 210, "made": true, "time": {"s": 58, "m": 19}}]}, {"percentage": 0, "id": 9639305, "shots": []}, {"percentage": 0, "id": 9639311, "shots": []}, {"percentage": 0, "id": 9639313, "shots": [{"y": 86, "x": 254, "made": false, "time": {"s": 23, "m": 19}}]}, {"percentage": 0, "id": 9639317, "shots": []}, {"percentage": 0, "id": 9639319, "shots": [{"y": 58, "x": 134, "made": true, "time": {"s": 45, "m": 13}}]}, {"percentage": 0, "id": 9639323, "shots": []}], "percentage": 41.54}, "homeTeam": {"players": [{"percentage": 66.67, "id": 9639273, "shots": [{"y": 43, "x": 122, "made": false, "time": {"s": 45, "m": 16}}, {"y": 38, "x": 114, "made": false, "time": {"s": 20, "m": 18}}]}, {"percentage": 40, "id": 9639259, "shots": [{"y": 46, "x": 131, "made": false, "time": {"s": 0, "m": 15}}, {"y": 35, "x": 59, "made": false, "time": {"s": 44, "m": 17}}, {"y": 44, "x": 131, "made": true, "time": {"s": 34, "m": 19}}]}, {"percentage": 50, "id": 9639271, "shots": [{"y": 61, "x": 256, "made": false, "time": {"s": 19, "m": 12}}, {"y": 149, "x": 192, "made": true, "time": {"s": 59, "m": 13}}]}, {"percentage": 57.14, "id": 9639281, "shots": [{"y": 27, "x": 12, "made": true, "time": {"s": 52, "m": 10}}, {"y": 74, "x": 259, "made": false, "time": {"s": 2, "m": 12}}]}, {"percentage": 42.86, "id": 9639265, "shots": []}, {"percentage": 80, "id": 9639289, "shots": [{"y": 41, "x": 162, "made": true, "time": {"s": 12, "m": 19}}]}, {"percentage": 25, "id": 9639287, "shots": []}, {"percentage": 0, "id": 9639275, "shots": []}, {"percentage": 0, "id": 9639267, "shots": [{"y": 39, "x": 129, "made": true, "time": {"s": 25, "m": 11}}]}, {"percentage": 0, "id": 9639269, "shots": [{"y": 88, "x": 76, "made": false, "time": {"s": 2, "m": 16}}]}, {"percentage": 0, "id": 9639277, "shots": []}, {"percentage": 0, "id": 9639285, "shots": [{"y": 35, "x": 132, "made": true, "time": {"s": 5, "m": 16}}]}], "percentage": 48.15}, "number": "2"}, "4": {"awayTeam": {"players": [{"percentage": 40, "id": 9639293, "shots": []}, {"percentage": 0, "id": 9639295, "shots": [{"y": 151, "x": 93, "made": false, "time": {"s": 21, "m": 39}}]}, {"percentage": 50, "id": 9639297, "shots": [{"y": 44, "x": 165, "made": false, "time": {"s": 47, "m": 30}}, {"y": 45, "x": 136, "made": false, "time": {"s": 51, "m": 36}}]}, {"percentage": 0, "id": 9639299, "shots": [{"y": 141, "x": 70, "made": false, "time": {"s": 54, "m": 37}}]}, {"percentage": 37.5, "id": 9639301, "shots": []}, {"percentage": 40, "id": 9639303, "shots": [{"y": 40, "x": 50, "made": false, "time": {"s": 2, "m": 33}}, {"y": 117, "x": 45, "made": true, "time": {"s": 34, "m": 34}}, {"y": 103, "x": 174, "made": true, "time": {"s": 2, "m": 35}}, {"y": 158, "x": 152, "made": true, "time": {"s": 41, "m": 35}}]}, {"percentage": 0, "id": 9639305, "shots": []}, {"percentage": 0, "id": 9639311, "shots": [{"y": 43, "x": 226, "made": false, "time": {"s": 9, "m": 36}}]}, {"percentage": 0, "id": 9639313, "shots": [{"y": 43, "x": 146, "made": true, "time": {"s": 25, "m": 39}}]}, {"percentage": 0, "id": 9639317, "shots": []}, {"percentage": 0, "id": 9639319, "shots": [{"y": 35, "x": 152, "made": false, "time": {"s": 50, "m": 37}}, {"y": 34, "x": 148, "made": true, "time": {"s": 48, "m": 38}}, {"y": 40, "x": 120, "made": false, "time": {"s": 53, "m": 39}}]}, {"percentage": 0, "id": 9639323, "shots": [{"y": 35, "x": 150, "made": false, "time": {"s": 12, "m": 32}}, {"y": 92, "x": 255, "made": false, "time": {"s": 47, "m": 33}}, {"y": 43, "x": 124, "made": true, "time": {"s": 15, "m": 37}}, {"y": 158, "x": 163, "made": false, "time": {"s": 22, "m": 38}}]}], "percentage": 41.54}, "homeTeam": {"players": [{"percentage": 66.67, "id": 9639273, "shots": []}, {"percentage": 40, "id": 9639259, "shots": [{"y": 94, "x": 188, "made": true, "time": {"s": 29, "m": 35}}, {"y": 105, "x": 251, "made": false, "time": {"s": 57, "m": 36}}]}, {"percentage": 50, "id": 9639271, "shots": [{"y": 37, "x": 131, "made": true, "time": {"s": 6, "m": 34}}]}, {"percentage": 57.14, "id": 9639281, "shots": []}, {"percentage": 42.86, "id": 9639265, "shots": [{"y": 129, "x": 225, "made": false, "time": {"s": 44, "m": 39}}]}, {"percentage": 80, "id": 9639289, "shots": [{"y": 42, "x": 120, "made": true, "time": {"s": 13, "m": 31}}]}, {"percentage": 25, "id": 9639287, "shots": [{"y": 41, "x": 124, "made": true, "time": {"s": 22, "m": 32}}, {"y": 122, "x": 123, "made": false, "time": {"s": 39, "m": 38}}]}, {"percentage": 0, "id": 9639275, "shots": [{"y": 44, "x": 143, "made": false, "time": {"s": 24, "m": 35}}]}, {"percentage": 0, "id": 9639267, "shots": []}, {"percentage": 0, "id": 9639269, "shots": [{"y": 37, "x": 185, "made": false, "time": {"s": 38, "m": 30}}]}, {"percentage": 0, "id": 9639277, "shots": []}, {"percentage": 0, "id": 9639285, "shots": [{"y": 101, "x": 254, "made": false, "time": {"s": 57, "m": 32}}, {"y": 46, "x": 166, "made": false, "time": {"s": 26, "m": 33}}, {"y": 54, "x": 15, "made": false, "time": {"s": 25, "m": 36}}]}], "percentage": 48.15}, "number": "4"}}}, "config": {"hash": "8e0e94f8-ec3c-4581-b07c-45c703a7dd75"}, "success": 1}