{"uid":131,"content":{"full":{"Competitors":[{"Color":"#0765c6","Stats":{"Leaders":{"Points":{"Id":"P_114476","Value":"20"},"Rebounds":{"Id":"P_114476","Value":"6"},"Assists":{"Id":"P_121018","Value":"5"}},"A_BL":0,"A_BLS":"","A_BR":7,"A_BRS":"20-24","A_FBP":11,"A_PAT":13,"A_PIP":28,"A_SCP":0,"T_DR":3,"T_OR":0,"T_PF":0,"T_REB":3,"T_TO":1,"A_TL":"00:00","T_TL":"00:00","A_ACT":0,"A_TOD":5,"A_TOT":3,"A_PFB":34,"A_FOUL":4,"AS":19,"BS":3,"DR":16,"FD":20,"FG2A":50,"FG2M":18,"FG2P":36,"FG3A":14,"FG3M":5,"FG3P":35.7,"FGA":64,"FGM":23,"FGP":35.9,"FTA":17,"FTM":13,"FTP":76.5,"OR":8,"PF":20,"PTS":64,"REB":24,"ST":13,"TO":18,"EFF":0},"Id":"T_375","Officials":[{"Id":"O_25108"},{"Id":"O_503295"}],"Periods":[{"Id":"Q1","Score":"16"},{"Id":"Q2","Score":"19"},{"Id":"Q3","Score":"13"},{"Id":"Q4","Score":"16"}],"Score":"64","Children":[{"Stats":{"Lead":{"BS":true},"CB":false,"PM":-5,"TP":"06:09","Starter":false,"AS":0,"BS":1,"DR":0,"FD":0,"FG2A":3,"FG2M":1,"FG2P":33.3,"FG3A":0,"FG3M":0,"FG3P":0,"FGA":3,"FGM":1,"FGP":33.3,"FTA":0,"FTM":0,"FTP":0,"OR":2,"PF":2,"PTS":2,"REB":2,"ST":1,"TO":0,"EFF":0},"Id":"P_114482","Name":"AOUICHI","Nationality":"TUN","PeriodScores":{}},{"Stats":{"Lead":{"AS":true,"TO":true},"CB":true,"PM":-18,"TP":"22:35","Starter":false,"AS":5,"BS":1,"DR":1,"FD":3,"FG2A":4,"FG2M":1,"FG2P":25,"FG3A":2,"FG3M":0,"FG3P":0,"FGA":6,"FGM":1,"FGP":16.7,"FTA":2,"FTM":1,"FTP":50,"OR":2,"PF":2,"PTS":3,"REB":3,"ST":1,"TO":4,"EFF":0},"Id":"P_121018","Name":"METHNANI","Nationality":"TUN","PeriodScores":{}},{"Stats":{"Lead":{"FG2M":true,"FTM":true,"PF":true,"ST":true},"START":"*","CB":true,"PM":-26,"TP":"34:19","Starter":true,"AS":2,"BS":0,"DR":1,"FD":4,"FG2A":11,"FG2M":5,"FG2P":45.5,"FG3A":0,"FG3M":0,"FG3P":0,"FGA":11,"FGM":5,"FGP":45.5,"FTA":5,"FTM":5,"FTP":100,"OR":0,"PF":3,"PTS":15,"REB":1,"ST":2,"TO":4,"EFF":0},"Id":"P_107470","Name":"GANNOUNI","Nationality":"TUN","PeriodScores":{}},{"Stats":{"Lead":{},"START":"*","CB":false,"PM":-28,"TP":"23:35","Starter":true,"AS":1,"BS":0,"DR":1,"FD":3,"FG2A":8,"FG2M":3,"FG2P":37.5,"FG3A":2,"FG3M":0,"FG3P":0,"FGA":10,"FGM":3,"FGP":30,"FTA":3,"FTM":2,"FTP":66.7,"OR":0,"PF":1,"PTS":8,"REB":1,"ST":2,"TO":3,"EFF":0},"Id":"P_114478","Name":"BHOURI","Nationality":"TUN","PeriodScores":{}},{"Stats":{"Lead":{"FG3M":true,"FGM":true,"REB":true,"DR":true,"FD":true,"PTS":true},"CB":true,"PM":-19,"TP":"33:26","Starter":false,"AS":4,"BS":0,"DR":6,"FD":6,"FG2A":7,"FG2M":4,"FG2P":57.1,"FG3A":5,"FG3M":3,"FG3P":60,"FGA":12,"FGM":7,"FGP":58.3,"FTA":3,"FTM":3,"FTP":100,"OR":0,"PF":3,"PTS":20,"REB":6,"ST":1,"TO":1,"EFF":0},"Id":"P_114476","Name":"DHIF","Nationality":"TUN","PeriodScores":{}},{"Stats":{"Lead":{},"CB":false,"PM":0,"TP":"01:05","Starter":false,"AS":0,"BS":0,"DR":0,"FD":0,"FG2A":1,"FG2M":0,"FG2P":0,"FG3A":0,"FG3M":0,"FG3P":0,"FGA":1,"FGM":0,"FGP":0,"FTA":0,"FTM":0,"FTP":0,"OR":0,"PF":1,"PTS":0,"REB":0,"ST":1,"TO":1,"EFF":0},"Id":"P_107481","Name":"JAWADI","Nationality":"TUN","PeriodScores":{}},{"Stats":{"Lead":{},"CB":true,"PM":-6,"TP":"14:08","Starter":false,"AS":2,"BS":0,"DR":0,"FD":1,"FG2A":1,"FG2M":0,"FG2P":0,"FG3A":2,"FG3M":1,"FG3P":50,"FGA":3,"FGM":1,"FGP":33.3,"FTA":2,"FTM":1,"FTP":50,"OR":0,"PF":2,"PTS":4,"REB":0,"ST":1,"TO":1,"EFF":0},"Id":"P_121017","Name":"RASSIL","Nationality":"TUN","PeriodScores":{}},{"Stats":{"Lead":{},"CB":false,"PM":-3,"TP":"10:42","Starter":false,"AS":1,"BS":0,"DR":0,"FD":1,"FG2A":3,"FG2M":0,"FG2P":0,"FG3A":3,"FG3M":1,"FG3P":33.3,"FGA":6,"FGM":1,"FGP":16.7,"FTA":0,"FTM":0,"FTP":0,"OR":0,"PF":0,"PTS":3,"REB":0,"ST":2,"TO":0,"EFF":0},"Id":"P_107483","Name":"HAJRI","Nationality":"TUN","PeriodScores":{}},{"Stats":{"Lead":{"OR":true},"START":"*","CB":false,"PM":-6,"TP":"09:19","Starter":true,"AS":1,"BS":0,"DR":0,"FD":1,"FG2A":2,"FG2M":0,"FG2P":0,"FG3A":0,"FG3M":0,"FG3P":0,"FGA":2,"FGM":0,"FGP":0,"FTA":2,"FTM":1,"FTP":50,"OR":3,"PF":1,"PTS":1,"REB":3,"ST":0,"TO":0,"EFF":0},"Id":"P_114477","Name":"ADDAMI","Nationality":"TUN","PeriodScores":{}},{"Stats":{"Lead":{},"START":"*","CB":true,"PM":-17,"TP":"19:03","Starter":true,"AS":1,"BS":0,"DR":1,"FD":1,"FG2A":5,"FG2M":3,"FG2P":60,"FG3A":0,"FG3M":0,"FG3P":0,"FGA":5,"FGM":3,"FGP":60,"FTA":0,"FTM":0,"FTP":0,"OR":1,"PF":3,"PTS":6,"REB":2,"ST":2,"TO":1,"EFF":0},"Id":"P_107949","Name":"SAIDANI","Nationality":"TUN","PeriodScores":{}},{"Stats":{"Lead":{},"START":"*","CB":false,"PM":-10,"TP":"05:34","Starter":true,"AS":2,"BS":0,"DR":1,"FD":0,"FG2A":1,"FG2M":0,"FG2P":0,"FG3A":0,"FG3M":0,"FG3P":0,"FGA":1,"FGM":0,"FGP":0,"FTA":0,"FTM":0,"FTP":0,"OR":0,"PF":1,"PTS":0,"REB":1,"ST":0,"TO":0,"EFF":0},"Id":"P_114481","Name":"BEN MAKHLOUF","Nationality":"TUN","PeriodScores":{}},{"Stats":{"Lead":{},"CB":false,"PM":-7,"TP":"15:05","Starter":false,"AS":0,"BS":1,"DR":2,"FD":0,"FG2A":4,"FG2M":1,"FG2P":25,"FG3A":0,"FG3M":0,"FG3P":0,"FGA":4,"FGM":1,"FGP":25,"FTA":0,"FTM":0,"FTP":0,"OR":0,"PF":1,"PTS":2,"REB":2,"ST":0,"TO":2,"EFF":0},"Id":"P_121019","Name":"GUEBELLAOUI","Nationality":"TUN","PeriodScores":{}}],"Name":"Tunisia","Nationality":"TUN","IsTeam":true,"PeriodScores":{"1":"16","2":"35","3":"37","4":"64"}},{"Color":"#3a6971","Stats":{"Leaders":{"Points":{"Id":"P_109841","Value":"18"},"Rebounds":{"Id":"P_109840","Value":"6"},"Assists":{"Id":"P_109832","Value":"6"}},"A_BL":36,"A_BLS":"91-55","A_BR":10,"A_BRS":"76-48","A_FBP":36,"A_PAT":19,"A_PIP":48,"A_SCP":17,"T_DR":2,"T_OR":0,"T_PF":0,"T_REB":2,"T_TO":1,"A_TL":"38:53","T_TL":"38:53","A_ACT":0,"A_TOD":5,"A_TOT":5,"A_PFB":36,"A_FOUL":3,"AS":24,"BS":7,"DR":37,"FD":20,"FG2A":36,"FG2M":26,"FG2P":72.2,"FG3A":28,"FG3M":10,"FG3P":35.7,"FGA":64,"FGM":36,"FGP":56.3,"FTA":15,"FTM":11,"FTP":73.3,"OR":13,"PF":20,"PTS":93,"REB":50,"ST":10,"TO":25,"EFF":0},"Id":"T_239","Officials":[{"Id":"O_502804"},{"Id":"O_19689"},{"Id":"O_502806"}],"Periods":[{"Id":"Q1","Score":"24"},{"Id":"Q2","Score":"29"},{"Id":"Q3","Score":"23"},{"Id":"Q4","Score":"17"}],"Score":"93","Children":[{"Stats":{"Lead":{"FG3M":true},"START":"*","CB":false,"PM":27,"TP":"13:14","Starter":true,"AS":1,"BS":0,"DR":2,"FD":1,"FG2A":5,"FG2M":4,"FG2P":80,"FG3A":4,"FG3M":2,"FG3P":50,"FGA":9,"FGM":6,"FGP":66.7,"FTA":0,"FTM":0,"FTP":0,"OR":0,"PF":1,"PTS":14,"REB":2,"ST":2,"TO":2,"EFF":0},"Id":"P_109119","Name":"VASILJEVIC","Nationality":"AUS","PeriodScores":{}},{"Stats":{"Lead":{},"CB":true,"PM":6,"TP":"15:26","Starter":false,"AS":2,"BS":0,"DR":0,"FD":1,"FG2A":3,"FG2M":3,"FG2P":100,"FG3A":3,"FG3M":1,"FG3P":33.3,"FGA":6,"FGM":4,"FGP":66.7,"FTA":1,"FTM":1,"FTP":100,"OR":1,"PF":0,"PTS":10,"REB":1,"ST":0,"TO":3,"EFF":0},"Id":"P_114011","Name":"GLOVER","Nationality":"AUS","PeriodScores":{}},{"Stats":{"Lead":{},"CB":false,"PM":-2,"TP":"20:03","Starter":false,"AS":1,"BS":1,"DR":2,"FD":2,"FG2A":2,"FG2M":1,"FG2P":50,"FG3A":6,"FG3M":2,"FG3P":33.3,"FGA":8,"FGM":3,"FGP":37.5,"FTA":0,"FTM":0,"FTP":0,"OR":0,"PF":3,"PTS":8,"REB":2,"ST":0,"TO":2,"EFF":0},"Id":"P_98938","Name":"KREBS","Nationality":"AUS","PeriodScores":{}},{"Stats":{"Lead":{"FTM":true,"REB":true,"DR":true,"FD":true},"START":"*","CB":true,"PM":26,"TP":"20:31","Starter":true,"AS":2,"BS":0,"DR":6,"FD":4,"FG2A":4,"FG2M":2,"FG2P":50,"FG3A":7,"FG3M":2,"FG3P":28.6,"FGA":11,"FGM":4,"FGP":36.4,"FTA":5,"FTM":3,"FTP":60,"OR":0,"PF":2,"PTS":13,"REB":6,"ST":2,"TO":3,"EFF":0},"Id":"P_109840","Name":"WILSON","Nationality":"AUS","PeriodScores":{}},{"Stats":{"Lead":{},"CB":true,"PM":1,"TP":"15:02","Starter":false,"AS":2,"BS":0,"DR":2,"FD":3,"FG2A":5,"FG2M":2,"FG2P":40,"FG3A":1,"FG3M":0,"FG3P":0,"FGA":6,"FGM":2,"FGP":33.3,"FTA":0,"FTM":0,"FTP":0,"OR":2,"PF":0,"PTS":4,"REB":4,"ST":0,"TO":2,"EFF":0},"Id":"P_118245","Name":"BLAGOJEVIC","Nationality":"AUS","PeriodScores":{}},{"Stats":{"Lead":{"AS":true,"TO":true,"ST":true},"CB":true,"PM":7,"TP":"24:12","Starter":false,"AS":6,"BS":0,"DR":3,"FD":1,"FG2A":2,"FG2M":2,"FG2P":100,"FG3A":3,"FG3M":1,"FG3P":33.3,"FGA":5,"FGM":3,"FGP":60,"FTA":2,"FTM":2,"FTP":100,"OR":1,"PF":1,"PTS":9,"REB":4,"ST":4,"TO":4,"EFF":0},"Id":"P_109832","Name":"MCDOWELL-WHITE","Nationality":"AUS","PeriodScores":{}},{"Stats":{"Lead":{"FG2M":true,"FGM":true,"PTS":true},"START":"*","CB":false,"PM":28,"TP":"15:17","Starter":true,"AS":3,"BS":1,"DR":4,"FD":3,"FG2A":6,"FG2M":6,"FG2P":100,"FG3A":2,"FG3M":1,"FG3P":50,"FGA":8,"FGM":7,"FGP":87.5,"FTA":3,"FTM":3,"FTP":100,"OR":2,"PF":0,"PTS":18,"REB":6,"ST":1,"TO":2,"EFF":0},"Id":"P_109841","Name":"WHITE","Nationality":"AUS","PeriodScores":{}},{"Stats":{"Lead":{},"START":"*","CB":false,"PM":28,"TP":"15:53","Starter":true,"AS":3,"BS":0,"DR":3,"FD":0,"FG2A":2,"FG2M":1,"FG2P":50,"FG3A":1,"FG3M":1,"FG3P":100,"FGA":3,"FGM":2,"FGP":66.7,"FTA":1,"FTM":1,"FTP":100,"OR":2,"PF":2,"PTS":6,"REB":5,"ST":1,"TO":0,"EFF":0},"Id":"P_109824","Name":"CLARK","Nationality":"AUS","PeriodScores":{}},{"Stats":{"Lead":{"PF":true},"CB":false,"PM":-2,"TP":"13:06","Starter":false,"AS":2,"BS":0,"DR":4,"FD":2,"FG2A":2,"FG2M":1,"FG2P":50,"FG3A":1,"FG3M":0,"FG3P":0,"FGA":3,"FGM":1,"FGP":33.3,"FTA":2,"FTM":1,"FTP":50,"OR":0,"PF":5,"PTS":3,"REB":4,"ST":0,"TO":2,"EFF":0},"Id":"P_118249","Name":"MCVEIGH","Nationality":"AUS","PeriodScores":{}},{"Stats":{"Lead":{"BS":true},"CB":false,"PM":12,"TP":"14:52","Starter":false,"AS":0,"BS":3,"DR":5,"FD":2,"FG2A":2,"FG2M":1,"FG2P":50,"FG3A":0,"FG3M":0,"FG3P":0,"FGA":2,"FGM":1,"FGP":50,"FTA":0,"FTM":0,"FTP":0,"OR":1,"PF":3,"PTS":2,"REB":6,"ST":0,"TO":2,"EFF":0},"Id":"P_118246","Name":"HUNTER","Nationality":"AUS","PeriodScores":{}},{"Stats":{"Lead":{"OR":true},"START":"*","CB":true,"PM":10,"TP":"18:25","Starter":true,"AS":1,"BS":1,"DR":3,"FD":1,"FG2A":3,"FG2M":3,"FG2P":100,"FG3A":0,"FG3M":0,"FG3P":0,"FGA":3,"FGM":3,"FGP":100,"FTA":1,"FTM":0,"FTP":0,"OR":3,"PF":0,"PTS":6,"REB":6,"ST":0,"TO":1,"EFF":0},"Id":"P_114010","Name":"GAK","Nationality":"AUS","PeriodScores":{}},{"Stats":{"Lead":{},"CB":false,"PM":4,"TP":"08:59","Starter":false,"AS":1,"BS":1,"DR":1,"FD":0,"FG2A":0,"FG2M":0,"FG2P":0,"FG3A":0,"FG3M":0,"FG3P":0,"FGA":0,"FGM":0,"FGP":0,"FTA":0,"FTM":0,"FTP":0,"OR":1,"PF":3,"PTS":0,"REB":2,"ST":0,"TO":1,"EFF":0},"Id":"P_98941","Name":"MCKAY","Nationality":"AUS","PeriodScores":{}}],"Name":"Australia","Nationality":"AUS","IsTeam":true,"PeriodScores":{"1":"24","2":"34","3":"57","4":"93"}}],"Officials":[{"Id":"O_16504"},{"Id":"O_15798"},{"Id":"O_18611"}],"ScoreList":[{"Items":[{"AC":"P2","C1":"P_109841","C2":"","Code":"2","SA":"0","SB":"2","Score":"0-2","Team":"T_239","Time":"09:52"},{"AC":"P2","C1":"P_109841","C2":"","Code":"4","SA":"0","SB":"4","Score":"0-4","Team":"T_239","Time":"08:20"},{"AC":"FT","C1":"P_109840","C2":"","Code":"5","SA":"0","SB":"5","Score":"0-5","Team":"T_239","Time":"07:41"},{"AC":"P2","C1":"P_109841","C2":"","Code":"7","SA":"0","SB":"7","Score":"0-7","Team":"T_239","Time":"07:26"},{"AC":"P2","C1":"P_107949","C2":"","Code":"5","SA":"2","SB":"7","Score":"2-7","Team":"T_375","Time":"07:08"},{"AC":"P2","C1":"P_109119","C2":"","Code":"7","SA":"2","SB":"9","Score":"2-9","Team":"T_239","Time":"06:38"},{"AC":"P2","C1":"P_114478","C2":"","Code":"5","SA":"4","SB":"9","Score":"4-9","Team":"T_375","Time":"06:14"},{"AC":"P2","C1":"P_109841","C2":"","Code":"7","SA":"4","SB":"11","Score":"4-11","Team":"T_239","Time":"06:07"},{"AC":"P2","C1":"P_114010","C2":"","Code":"9","SA":"4","SB":"13","Score":"4-13","Team":"T_239","Time":"05:38"},{"AC":"P2","C1":"P_109119","C2":"","Code":"11","SA":"4","SB":"15","Score":"4-15","Team":"T_239","Time":"05:14"},{"AC":"P3","C1":"P_114476","C2":"","Code":"8","SA":"7","SB":"15","Score":"7-15","Team":"T_375","Time":"04:57"},{"AC":"P3","C1":"P_114476","C2":"","Code":"5","SA":"10","SB":"15","Score":"10-15","Team":"T_375","Time":"04:07"},{"AC":"P3","C1":"P_98938","C2":"","Code":"8","SA":"10","SB":"18","Score":"10-18","Team":"T_239","Time":"03:42"},{"AC":"P2","C1":"P_107949","C2":"","Code":"6","SA":"12","SB":"18","Score":"12-18","Team":"T_375","Time":"03:23"},{"AC":"FT","C1":"P_118249","C2":"","Code":"7","SA":"12","SB":"19","Score":"12-19","Team":"T_239","Time":"03:19"},{"AC":"P2","C1":"P_118245","C2":"","Code":"9","SA":"12","SB":"21","Score":"12-21","Team":"T_239","Time":"01:46"},{"AC":"FT","C1":"P_121018","C2":"","Code":"8","SA":"13","SB":"21","Score":"13-21","Team":"T_375","Time":"01:31"},{"AC":"P3","C1":"P_109832","C2":"","Code":"11","SA":"13","SB":"24","Score":"13-24","Team":"T_239","Time":"01:10"},{"AC":"P2","C1":"P_114476","C2":"","Code":"9","SA":"15","SB":"24","Score":"15-24","Team":"T_375","Time":"00:57"},{"AC":"FT","C1":"P_114476","C2":"","Code":"8","SA":"16","SB":"24","Score":"16-24","Team":"T_375","Time":"00:57"}],"Period":"Q1"},{"Items":[{"AC":"P2","C1":"P_121019","C2":"","Code":"6","SA":"18","SB":"24","Score":"18-24","Team":"T_375","Time":"09:43"},{"AC":"P2","C1":"P_114476","C2":"","Code":"4","SA":"20","SB":"24","Score":"20-24","Team":"T_375","Time":"09:06"},{"AC":"P2","C1":"P_118249","C2":"","Code":"6","SA":"20","SB":"26","Score":"20-26","Team":"T_239","Time":"08:53"},{"AC":"P3","C1":"P_107483","C2":"","Code":"3","SA":"23","SB":"26","Score":"23-26","Team":"T_375","Time":"08:18"},{"AC":"P3","C1":"P_109824","C2":"","Code":"6","SA":"23","SB":"29","Score":"23-29","Team":"T_239","Time":"07:28"},{"AC":"FT","C1":"P_121017","C2":"","Code":"5","SA":"24","SB":"29","Score":"24-29","Team":"T_375","Time":"06:57"},{"AC":"P3","C1":"P_109841","C2":"","Code":"8","SA":"24","SB":"32","Score":"24-32","Team":"T_239","Time":"06:37"},{"AC":"P2","C1":"P_109119","C2":"","Code":"10","SA":"24","SB":"34","Score":"24-34","Team":"T_239","Time":"06:08"},{"AC":"P2","C1":"P_107470","C2":"","Code":"8","SA":"26","SB":"34","Score":"26-34","Team":"T_375","Time":"05:18"},{"AC":"P3","C1":"P_109119","C2":"","Code":"11","SA":"26","SB":"37","Score":"26-37","Team":"T_239","Time":"04:23"},{"AC":"P2","C1":"P_109119","C2":"","Code":"13","SA":"26","SB":"39","Score":"26-39","Team":"T_239","Time":"04:08"},{"AC":"FT","C1":"P_109840","C2":"","Code":"14","SA":"26","SB":"40","Score":"26-40","Team":"T_239","Time":"03:21"},{"AC":"FT","C1":"P_109840","C2":"","Code":"15","SA":"26","SB":"41","Score":"26-41","Team":"T_239","Time":"03:21"},{"AC":"P2","C1":"P_114482","C2":"","Code":"13","SA":"28","SB":"41","Score":"28-41","Team":"T_375","Time":"03:08"},{"AC":"FT","C1":"P_107470","C2":"","Code":"12","SA":"29","SB":"41","Score":"29-41","Team":"T_375","Time":"02:20"},{"AC":"FT","C1":"P_107470","C2":"","Code":"11","SA":"30","SB":"41","Score":"30-41","Team":"T_375","Time":"02:20"},{"AC":"P3","C1":"P_98938","C2":"","Code":"14","SA":"30","SB":"44","Score":"30-44","Team":"T_239","Time":"02:03"},{"AC":"P2","C1":"P_109832","C2":"","Code":"16","SA":"30","SB":"46","Score":"30-46","Team":"T_239","Time":"01:18"},{"AC":"P2","C1":"P_107470","C2":"","Code":"14","SA":"32","SB":"46","Score":"32-46","Team":"T_375","Time":"00:56"},{"AC":"FT","C1":"P_109832","C2":"","Code":"15","SA":"32","SB":"47","Score":"32-47","Team":"T_239","Time":"00:51"},{"AC":"FT","C1":"P_109832","C2":"","Code":"16","SA":"32","SB":"48","Score":"32-48","Team":"T_239","Time":"00:51"},{"AC":"P2","C1":"P_109841","C2":"","Code":"18","SA":"32","SB":"50","Score":"32-50","Team":"T_239","Time":"00:27"},{"AC":"FT","C1":"P_109841","C2":"","Code":"19","SA":"32","SB":"51","Score":"32-51","Team":"T_239","Time":"00:27"},{"AC":"FT","C1":"P_109841","C2":"","Code":"20","SA":"32","SB":"52","Score":"32-52","Team":"T_239","Time":"00:13"},{"AC":"FT","C1":"P_109841","C2":"","Code":"21","SA":"32","SB":"53","Score":"32-53","Team":"T_239","Time":"00:13"},{"AC":"FT","C1":"P_107470","C2":"","Code":"20","SA":"33","SB":"53","Score":"33-53","Team":"T_375","Time":"00:01"},{"AC":"FT","C1":"P_107470","C2":"","Code":"19","SA":"34","SB":"53","Score":"34-53","Team":"T_375","Time":"00:01"},{"AC":"FT","C1":"P_107470","C2":"","Code":"18","SA":"35","SB":"53","Score":"35-53","Team":"T_375","Time":"00:01"}],"Period":"Q2"},{"Items":[{"AC":"P2","C1":"P_109841","C2":"","Code":"20","SA":"35","SB":"55","Score":"35-55","Team":"T_239","Time":"09:36"},{"AC":"P2","C1":"P_107470","C2":"","Code":"18","SA":"37","SB":"55","Score":"37-55","Team":"T_375","Time":"09:18"},{"AC":"P2","C1":"P_109840","C2":"","Code":"20","SA":"37","SB":"57","Score":"37-57","Team":"T_239","Time":"09:07"},{"AC":"P2","C1":"P_114010","C2":"","Code":"22","SA":"37","SB":"59","Score":"37-59","Team":"T_239","Time":"07:38"},{"AC":"P3","C1":"P_109119","C2":"","Code":"25","SA":"37","SB":"62","Score":"37-62","Team":"T_239","Time":"07:32"},{"AC":"P2","C1":"P_114478","C2":"","Code":"23","SA":"39","SB":"62","Score":"39-62","Team":"T_375","Time":"06:50"},{"AC":"P2","C1":"P_114478","C2":"","Code":"21","SA":"41","SB":"62","Score":"41-62","Team":"T_375","Time":"05:51"},{"AC":"FT","C1":"P_114477","C2":"","Code":"20","SA":"42","SB":"62","Score":"42-62","Team":"T_375","Time":"05:12"},{"AC":"P2","C1":"P_118246","C2":"","Code":"22","SA":"42","SB":"64","Score":"42-64","Team":"T_239","Time":"04:53"},{"AC":"P2","C1":"P_107470","C2":"","Code":"20","SA":"44","SB":"64","Score":"44-64","Team":"T_375","Time":"04:30"},{"AC":"P2","C1":"P_109832","C2":"","Code":"22","SA":"44","SB":"66","Score":"44-66","Team":"T_239","Time":"04:03"},{"AC":"FT","C1":"P_114476","C2":"","Code":"21","SA":"45","SB":"66","Score":"45-66","Team":"T_375","Time":"03:47"},{"AC":"FT","C1":"P_114476","C2":"","Code":"20","SA":"46","SB":"66","Score":"46-66","Team":"T_375","Time":"03:47"},{"AC":"P2","C1":"P_107470","C2":"","Code":"18","SA":"48","SB":"66","Score":"48-66","Team":"T_375","Time":"02:50"},{"AC":"P2","C1":"P_114011","C2":"","Code":"20","SA":"48","SB":"68","Score":"48-68","Team":"T_239","Time":"02:36"},{"AC":"FT","C1":"P_114011","C2":"","Code":"21","SA":"48","SB":"69","Score":"48-69","Team":"T_239","Time":"02:36"},{"AC":"P2","C1":"P_109840","C2":"","Code":"23","SA":"48","SB":"71","Score":"48-71","Team":"T_239","Time":"01:43"},{"AC":"P2","C1":"P_118245","C2":"","Code":"25","SA":"48","SB":"73","Score":"48-73","Team":"T_239","Time":"01:19"},{"AC":"P3","C1":"P_109840","C2":"","Code":"28","SA":"48","SB":"76","Score":"48-76","Team":"T_239","Time":"00:14"}],"Period":"Q3"},{"Items":[{"AC":"P2","C1":"P_114476","C2":"","Code":"26","SA":"50","SB":"76","Score":"50-76","Team":"T_375","Time":"09:43"},{"AC":"P2","C1":"P_114010","C2":"","Code":"28","SA":"50","SB":"78","Score":"50-78","Team":"T_239","Time":"09:35"},{"AC":"P3","C1":"P_114476","C2":"","Code":"25","SA":"53","SB":"78","Score":"53-78","Team":"T_375","Time":"09:13"},{"AC":"P3","C1":"P_114011","C2":"","Code":"28","SA":"53","SB":"81","Score":"53-81","Team":"T_239","Time":"08:44"},{"AC":"FT","C1":"P_114478","C2":"","Code":"27","SA":"54","SB":"81","Score":"54-81","Team":"T_375","Time":"06:52"},{"AC":"FT","C1":"P_114478","C2":"","Code":"26","SA":"55","SB":"81","Score":"55-81","Team":"T_375","Time":"06:52"},{"AC":"P3","C1":"P_109840","C2":"","Code":"29","SA":"55","SB":"84","Score":"55-84","Team":"T_239","Time":"06:10"},{"AC":"P2","C1":"P_98938","C2":"","Code":"31","SA":"55","SB":"86","Score":"55-86","Team":"T_239","Time":"05:43"},{"AC":"P2","C1":"P_114011","C2":"","Code":"33","SA":"55","SB":"88","Score":"55-88","Team":"T_239","Time":"05:18"},{"AC":"P2","C1":"P_109824","C2":"","Code":"35","SA":"55","SB":"90","Score":"55-90","Team":"T_239","Time":"04:35"},{"AC":"FT","C1":"P_109824","C2":"","Code":"36","SA":"55","SB":"91","Score":"55-91","Team":"T_239","Time":"04:35"},{"AC":"P3","C1":"P_121017","C2":"","Code":"33","SA":"58","SB":"91","Score":"58-91","Team":"T_375","Time":"04:14"},{"AC":"P2","C1":"P_114011","C2":"","Code":"35","SA":"58","SB":"93","Score":"58-93","Team":"T_239","Time":"02:13"},{"AC":"P2","C1":"P_114476","C2":"","Code":"33","SA":"60","SB":"93","Score":"60-93","Team":"T_375","Time":"01:42"},{"AC":"P2","C1":"P_107949","C2":"","Code":"31","SA":"62","SB":"93","Score":"62-93","Team":"T_375","Time":"01:17"},{"AC":"P2","C1":"P_121018","C2":"","Code":"29","SA":"64","SB":"93","Score":"64-93","Team":"T_375","Time":"00:58"}],"Period":"Q4"}],"CurrentPeriod":"Q4","CurrentPeriodStatus":"S","WatchOn":[{"Name":"FIBA.COM","Url":"http://www.fiba.com/world/u19/2015/videos#tab=tv_broadcasters"}],"Status":"Event-999-","EventName":"2015 FIBA U19 World Championship","FederationCodes":{"EventId":"8043","GameId":"6","GroupId":"C","RoundId":"11700"},"Location":"Heraklion_HeraklionArena","PhaseName":"Group Phase","RC":"00:25","Rsc":{"Discipline":"BK","Event":"8043","Gender":"M","LongEvent":"BKM8043","Phase":"C","Unit":"6","Value":"11700-C-6"},"Site":"Heraklion Arena","Spect":0,"StartTime":181500000,"UnitName":"","Stats":{"DUR":"01:40","A_LC":0,"A_TT":0,"SPECT":0}}}}