{"sports_content":{"sports_meta":{"date_time":"20160719 0408","season_meta":{"calendar_date":"20160719","season_year":"2016","stats_season_year":"2016","stats_season_id":"22016","stats_season_stage":"2","roster_season_year":"2016","schedule_season_year":"2016","standings_season_year":"2016","season_id":"22016","display_year":"2016","display_season":"Regular Season","season_stage":"2","league_id":"00"},"next":{"url":"http:\/\/data.nba.com\/data\/15m\/json\/sl\/cms\/noseason\/players\/sl_mateusz_ponitka\/gamelog.json"}},"player":{"player_code":"sl_mateusz_ponitka","game_log":{"game":[{"id":"1521600062","result":"L","team_score":"81","opp_team_score":"82","game_date":"20160716","vis_hom":"H","opp_team_abbrev":"PHX","opp_team_code":"suns","playoff_round":"","game_type":"2","minutes":"24","field_goals":"2-4","three_pointers":"0-0","free_throws":"0-2","rebounds":"10","offensive_rebounds":"6","defensive_rebounds":"4","assists":"1","steals":"2","blocked_shots":"0","turnovers":"1","personal_fouls":"4","points":"4","efficiency":"+12.00","game_month":"7"},{"id":"1521600049","result":"W","team_score":"80","opp_team_score":"60","game_date":"20160714","vis_hom":"H","opp_team_abbrev":"UTA","opp_team_code":"jazz","playoff_round":"","game_type":"2","minutes":"22","field_goals":"2-3","three_pointers":"0-0","free_throws":"0-0","rebounds":"1","offensive_rebounds":"0","defensive_rebounds":"1","assists":"1","steals":"2","blocked_shots":"0","turnovers":"2","personal_fouls":"4","points":"4","efficiency":"+5.00","game_month":"7"},{"id":"1521600025","result":"L","team_score":"81","opp_team_score":"92","game_date":"20160711","vis_hom":"H","opp_team_abbrev":"MIA","opp_team_code":"heat","playoff_round":"","game_type":"2","minutes":"9","field_goals":"0-1","three_pointers":"0-0","free_throws":"0-0","rebounds":"3","offensive_rebounds":"1","defensive_rebounds":"2","assists":"0","steals":"0","blocked_shots":"0","turnovers":"1","personal_fouls":"3","points":"0","efficiency":"+1.00","game_month":"7"},{"id":"1521600009","result":"W","team_score":"106","opp_team_score":"62","game_date":"20160709","vis_hom":"V","opp_team_abbrev":"MEM","opp_team_code":"grizzlies","playoff_round":"","game_type":"2","minutes":"19","field_goals":"1-4","three_pointers":"0-1","free_throws":"0-0","rebounds":"10","offensive_rebounds":"5","defensive_rebounds":"5","assists":"0","steals":"1","blocked_shots":"0","turnovers":"3","personal_fouls":"1","points":"2","efficiency":"+7.00","game_month":"7"}]}}}}