{"sports_content":{"sports_meta":{"date_time":"20160719 0414","season_meta":{"calendar_date":"20160719","season_year":"2016","stats_season_year":"2016","stats_season_id":"22016","stats_season_stage":"2","roster_season_year":"2016","schedule_season_year":"2016","standings_season_year":"2016","season_id":"22016","display_year":"2016","display_season":"Regular Season","season_stage":"2","league_id":"00"},"next":{"url":"http:\/\/data.nba.com\/data\/15m\/json\/sl\/cms\/noseason\/players\/sl_sam_thompson\/gamelog.json"}},"player":{"player_code":"sl_sam_thompson","game_log":{"game":[{"id":"1421600021","result":"L","team_score":"92","opp_team_score":"97","game_date":"20160708","vis_hom":"H","opp_team_abbrev":"DAL","opp_team_code":"mavericks","playoff_round":"","game_type":"2","minutes":"25","field_goals":"3-8","three_pointers":"0-3","free_throws":"0-0","rebounds":"4","offensive_rebounds":"0","defensive_rebounds":"4","assists":"1","steals":"0","blocked_shots":"1","turnovers":"1","personal_fouls":"3","points":"6","efficiency":"+6.00","game_month":"7"},{"id":"1421600011","result":"W","team_score":"78","opp_team_score":"74","game_date":"20160704","vis_hom":"V","opp_team_abbrev":"OKC","opp_team_code":"thunder","playoff_round":"","game_type":"2","minutes":"5","field_goals":"0-0","three_pointers":"0-0","free_throws":"0-0","rebounds":"1","offensive_rebounds":"0","defensive_rebounds":"1","assists":"0","steals":"0","blocked_shots":"0","turnovers":"0","personal_fouls":"0","points":"0","efficiency":"+1.00","game_month":"7"},{"id":"1421600002","result":"L","team_score":"74","opp_team_score":"79","game_date":"20160702","vis_hom":"V","opp_team_abbrev":"ORW","opp_team_code":"white","playoff_round":"","game_type":"2","minutes":"2","field_goals":"0-1","three_pointers":"0-0","free_throws":"0-0","rebounds":"0","offensive_rebounds":"0","defensive_rebounds":"0","assists":"0","steals":"0","blocked_shots":"0","turnovers":"0","personal_fouls":"1","points":"0","efficiency":"-1.00","game_month":"7"}]}}}}